shell_craft/__init__.py
shell_craft/__main__.py
shell_craft/configuration.py
shell_craft/cli/__init__.py
shell_craft/cli/commands.py
shell_craft/cli/github.py
shell_craft/cli/main.py
shell_craft/cli/parser.py
shell_craft/cli/prompt.py
shell_craft/cli/types.py
shell_craft/factories/__init__.py
shell_craft/factories/prompt.py
shell_craft/prompts/__init__.py
shell_craft/prompts/languages.py
shell_craft/prompts/prompt.py
shell_craft/prompts/templates.py
shell_craft/services/__init__.py
shell_craft/services/service.py
shell_craft/services/openai/__init__.py
shell_craft/services/openai/service.py
shell_craft/services/openai/settings.py
openai_shell_craft-1.2.0.dist-info/LICENSE
openai_shell_craft-1.2.0.dist-info/METADATA
openai_shell_craft-1.2.0.dist-info/WHEEL
openai_shell_craft-1.2.0.dist-info/entry_points.txt
openai_shell_craft-1.2.0.dist-info/top_level.txt
openai_shell_craft-1.2.0.dist-info/RECORD
