Metadata-Version: 2.1
Name: openai-shell-craft
Version: 1.2.0
Summary: Generating shell commands and code using natural language models (OpenAI ChatGPT).
Author-email: Johnathan Irvin <irvinjohnathan@gmail.com>
Project-URL: Homepage, https://github.com/JohnnyIrvin/shell-craft
Project-URL: Bug Tracker, https://github.com/JohnnyIrvin/shell-craft/issues
Classifier: Programming Language :: Python :: 3
Classifier: License :: OSI Approved :: MIT License
Classifier: Operating System :: OS Independent
Requires-Python: >=3.9
License-File: LICENSE
Requires-Dist: openai
Requires-Dist: psutil
